pfx/__init__.py
pfx/main.py
PFX-1.0.3.dist-info/LICENSE
PFX-1.0.3.dist-info/METADATA
PFX-1.0.3.dist-info/WHEEL
PFX-1.0.3.dist-info/entry_points.txt
PFX-1.0.3.dist-info/top_level.txt
PFX-1.0.3.dist-info/RECORD
