Metadata-Version: 2.1
Name: PFX
Version: 1.0.3
Summary: PFX or Python-Effects is a PyPI package for adding effects onto Image Processing
Home-page: https://github.com/prashanth-up/PFX
Author: Prashanth Umapathy
Author-email: ujprashant@gmail.com
License: UNKNOWN
Platform: UNKNOWN
Classifier: Programming Language :: Python :: 3
Classifier: License :: OSI Approved :: MIT License
Classifier: Operating System :: OS Independent
Requires-Python: >=3.6
Requires-Dist: pillow
